mcp_taxii/__init__.py
mcp_taxii/server.py
mcp_taxii/clients/__init__.py
mcp_taxii/clients/base.py
mcp_taxii/clients/taxii_20.py
mcp_taxii/clients/taxii_21.py
mcp_taxii-0.1.0.dist-info/METADATA
mcp_taxii-0.1.0.dist-info/WHEEL
mcp_taxii-0.1.0.dist-info/entry_points.txt
mcp_taxii-0.1.0.dist-info/licenses/LICENSE
mcp_taxii-0.1.0.dist-info/RECORD
