Metadata-Version: 2.4
Name: mcp-taxii
Version: 0.1.0
Summary: MCP Server that serves as a TAXII Client for AI Agents
Project-URL: Homepage, https://github.com/davydany/mcp-taxii
Project-URL: Documentation, https://github.com/davydany/mcp-taxii#readme
Project-URL: Repository, https://github.com/davydany/mcp-taxii.git
Project-URL: Issues, https://github.com/davydany/mcp-taxii/issues
Project-URL: Changelog, https://github.com/davydany/mcp-taxii/releases
Author: MCP TAXII Contributors
License: MIT
License-File: LICENSE
Keywords: ai,claude,cybersecurity,mcp,stix,taxii,threat-intelligence
Classifier: Development Status :: 3 - Alpha
Classifier: Intended Audience :: Developers
Classifier: Intended Audience :: Information Technology
Classifier: License :: OSI Approved :: MIT License
Classifier: Operating System :: OS Independent
Classifier: Programming Language :: Python :: 3
Classifier: Programming Language :: Python :: 3.11
Classifier: Programming Language :: Python :: 3.12
Classifier: Programming Language :: Python :: 3.13
Classifier: Topic :: Security
Classifier: Topic :: Software Development :: Libraries :: Python Modules
Classifier: Typing :: Typed
Requires-Python: >=3.11
Requires-Dist: fastmcp>=0.1.0
Requires-Dist: httpx>=0.25.0
Requires-Dist: pydantic>=2.0.0
Requires-Dist: python-dotenv>=1.0.0
Requires-Dist: stix2>=3.0.0
Requires-Dist: taxii2-client>=2.3.0
Provides-Extra: dev
Requires-Dist: pytest-asyncio>=0.21.0; extra == 'dev'
Requires-Dist: pytest-cov>=4.1.0; extra == 'dev'
Requires-Dist: pytest>=7.4.0; extra == 'dev'
Requires-Dist: ruff>=0.1.0; extra == 'dev'
Provides-Extra: test-server
Requires-Dist: fastapi>=0.104.0; extra == 'test-server'
Requires-Dist: sqlalchemy>=2.0.0; extra == 'test-server'
Requires-Dist: uvicorn[standard]>=0.24.0; extra == 'test-server'
